MANIFEST.in
README.rst
VERSION
setup.py
mapactionpy_qgis/__init__.py
mapactionpy_qgis.egg-info/PKG-INFO
mapactionpy_qgis.egg-info/SOURCES.txt
mapactionpy_qgis.egg-info/dependency_links.txt
mapactionpy_qgis.egg-info/not-zip-safe
mapactionpy_qgis.egg-info/top_level.txt
mapactionpy_qgis/tests/__init__.py
mapactionpy_qgis/tests/test_mapactionpy_qgis.py