Metadata-Version: 2.1
Name: mapactionpy-qgis
Version: 0.2
Summary: Used to drive QGIS
Home-page: http://github.com/mapaction/mapactionpy_qgis
Author: MapAction
Author-email: github@mapaction.com
License: GPL3
Platform: UNKNOWN
Classifier: Development Status :: 2 - Pre-Alpha
Classifier: Programming Language :: Python :: 3
Classifier: License :: OSI Approved :: GNU General Public License v3 (GPLv3)
Classifier: Operating System :: OS Independent
